sumologic/__init__.py
sumologic/client.py
sumologic/collectors.py
sumologic/search.py
sumologic/utils.py
sumologic-0.1.4.dist-info/DESCRIPTION.rst
sumologic-0.1.4.dist-info/METADATA
sumologic-0.1.4.dist-info/RECORD
sumologic-0.1.4.dist-info/WHEEL
sumologic-0.1.4.dist-info/metadata.json
sumologic-0.1.4.dist-info/top_level.txt
