Metadata-Version: 2.0
Name: sumologic
Version: 0.1.4
Summary: Python library for working with the Sumo Logic api.
Home-page: https://github.com/sijis/sumologic-python
Author: Sijis Aviles
Author-email: sijis.aviles@gmail.com
License: UNKNOWN
Download-URL: https://github.com/sijis/sumologic-python
Keywords: sumologic api python
Platform: OS Independent
Classifier: Development Status :: 4 - Beta
Classifier: Intended Audience :: Developers
Classifier: Programming Language :: Python :: 2.7
Classifier: Programming Language :: Python :: 3.3
Classifier: Programming Language :: Python :: 3.4
Classifier: Programming Language :: Python :: 3.5
Classifier: Operating System :: OS Independent
Requires-Dist: requests
